vesync_outlet/__init__.py
vesync_outlet/models.py
vesync_outlet-0.1.1.dist-info/LICENSE
vesync_outlet-0.1.1.dist-info/METADATA
vesync_outlet-0.1.1.dist-info/WHEEL
vesync_outlet-0.1.1.dist-info/top_level.txt
vesync_outlet-0.1.1.dist-info/RECORD
