Metadata-Version: 2.1
Name: vesync-outlet
Version: 0.1.1
Summary: vesync-outlet is a library to control Vesync wifi outlets
Home-page: https://github.com/jeffleary00/vesync-outlet
Author: Jeff Leary
Author-email: sillymonkeysoftware@gmail.com
License: MIT
Keywords: vesync,iot
Platform: UNKNOWN
Classifier: License :: OSI Approved :: MIT License
Classifier: Intended Audience :: Developers
Classifier: Intended Audience :: End Users/Desktop
Classifier: Natural Language :: English
Classifier: Programming Language :: Python :: 2.7
Classifier: Programming Language :: Python :: 3.0
Requires-Dist: requests (>=2.6.0)
